[
  {
    "demand": 0,
    "x": -64,
    "y": 11
  },
  {
    "demand": 0,
    "x": 1,
    "y": 0
  },
  {
    "demand": 0,
    "x": 69,
    "y": -8
  },
  {
    "demand": 175,
    "x": -22,
    "y": 3
  },
  {
    "demand": 186,
    "x": -38,
    "y": 7
  },
  {
    "demand": 273,
    "x": 23,
    "y": 62
  },
  {
    "demand": 205,
    "x": 82,
    "y": -63
  },
  {
    "demand": 268,
    "x": 16,
    "y": -97
  },
  {
    "demand": 237,
    "x": 69,
    "y": -91
  },
  {
    "demand": 169,
    "x": -59,
    "y": -63
  },
  {
    "demand": 111,
    "x": -62,
    "y": 33
  },
  {
    "demand": 221,
    "x": -58,
    "y": -90
  },
  {
    "demand": 213,
    "x": 10,
    "y": 35
  },
  {
    "demand": 223,
    "x": -91,
    "y": 4
  },
  {
    "demand": 125,
    "x": 41,
    "y": -31
  },
  {
    "demand": 221,
    "x": -41,
    "y": -96
  },
  {
    "demand": 290,
    "x": -54,
    "y": -52
  },
  {
    "demand": 238,
    "x": 62,
    "y": 56
  },
  {
    "demand": 286,
    "x": 4,
    "y": 11
  },
  {
    "demand": 210,
    "x": 30,
    "y": 61
  },
  {
    "demand": 214,
    "x": -31,
    "y": 90
  },
  {
    "demand": 270,
    "x": 97,
    "y": -61
  },
  {
    "demand": 196,
    "x": -36,
    "y": -80
  },
  {
    "demand": 127,
    "x": 64,
    "y": -87
  },
  {
    "demand": 233,
    "x": -41,
    "y": 72
  },
  {
    "demand": 233,
    "x": 82,
    "y": 75
  },
  {
    "demand": 105,
    "x": 43,
    "y": 10
  },
  {
    "demand": 289,
    "x": -85,
    "y": 94
  },
  {
    "demand": 276,
    "x": -22,
    "y": -24
  },
  {
    "demand": 198,
    "x": -28,
    "y": 38
  },
  {
    "demand": 274,
    "x": 35,
    "y": 80
  },
  {
    "demand": 214,
    "x": -97,
    "y": 40
  },
  {
    "demand": 130,
    "x": -92,
    "y": 43
  },
  {
    "demand": 283,
    "x": -45,
    "y": 94
  },
  {
    "demand": 135,
    "x": -76,
    "y": -18
  },
  {
    "demand": 284,
    "x": 62,
    "y": 2
  },
  {
    "demand": 235,
    "x": -95,
    "y": 21
  },
  {
    "demand": 150,
    "x": -48,
    "y": 87
  },
  {
    "demand": 296,
    "x": 4,
    "y": -47
  },
  {
    "demand": 262,
    "x": 24,
    "y": 18
  },
  {
    "demand": 182,
    "x": 93,
    "y": 91
  },
  {
    "demand": 132,
    "x": 97,
    "y": -71
  },
  {
    "demand": 132,
    "x": -47,
    "y": -44
  },
  {
    "demand": 132,
    "x": -81,
    "y": 73
  },
  {
    "demand": 215,
    "x": 3,
    "y": -13
  },
  {
    "demand": 211,
    "x": -79,
    "y": 90
  },
  {
    "demand": 274,
    "x": 53,
    "y": 16
  },
  {
    "demand": 116,
    "x": 92,
    "y": -33
  },
  {
    "demand": 293,
    "x": 63,
    "y": -18
  },
  {
    "demand": 186,
    "x": 23,
    "y": -2
  },
  {
    "demand": 124,
    "x": 17,
    "y": -17
  },
  {
    "demand": 103,
    "x": -33,
    "y": -39
  },
  {
    "demand": 153,
    "x": 1,
    "y": -74
  }
]